{
  "title": "Chléb Šumava",
  "summary": "Tradiční pecen s vylepšenou strukturou díky přesně časované autolýze a důrazu na teplotu středu střídky.",
  "ingredients": [
    "20 g aktivního žitného kvásku",
    "200 g žitné chlebové mouky",
    "200 g vody pro rozkvas",
    "500 g pšeničné chlebové mouky",
    "250 g vody pro autolýzu",
    "14 g mořské soli",
    "10 g drceného kmínu"
  ],
  "instructions": [
    "Připravte rozkvas smícháním surovin a nechte jej fermentovat, dokud nezdvojnásobí objem.",
    "Teprve po uzrání rozkvasu smíchejte mouku s vodou určenou pro autolýzu a nechte směs odpočívat pro hydrataci bílkovin.",
    "Ke směsi přidejte vyzrálý rozkvas, sůl a kmín. Těsto důkladně hněťte, dokud nevznikne hladká a pružná hmota.",
    "Během primární fermentace provádějte pravidelné překlady, aby těsto získalo vnitřní strukturu.",
    "Těsto stočte do pevného bochníku a nechte v ošatce dokynout do plného objemu.",
    "Pečte v prudce vyhřáté troubě se zapařením pro vytvoření křupavé kůrky.",
    "Po odvětrání páry snižte teplotu a dopečte, dokud střídka nedosáhne požadované teploty."
  ],
  "applianceTips": "Pro dosažení profesionálního výsledku použijte litinový hrnec, který v troubě imituje parní komoru a drží stabilní teplotu.",
  "expertJustification": "Oddělením autolýzy od doby fermentace rozkvasu zabráníme nadměrnému změkčení těsta enzymy, což vede k lepšímu objemu a struktuře střídky.",
  "applianceType": "Trouba s funkcí páry nebo litinový hrnec",
  "cookingTime": "540 min",
  "difficulty": "Střední",
  "category": "Pečivo",
  "id": "gen-1783540977144",
  "updatedAt": "2026-07-13T11:58:48.094Z",
  "estimatedCookingTime": "540 min"
}